spec2sdk/__init__.py
spec2sdk/base.py
spec2sdk/client/__init__.py
spec2sdk/client/generators.py
spec2sdk/client/templates/api.j2
spec2sdk/client/templates/api_client.j2
spec2sdk/client/templates/http_client.j2
spec2sdk/client/views.py
spec2sdk/main.py
spec2sdk/models/__init__.py
spec2sdk/models/annotations.py
spec2sdk/models/converters.py
spec2sdk/models/entities.py
spec2sdk/models/generators.py
spec2sdk/models/identifiers.py
spec2sdk/models/imports.py
spec2sdk/models/predicates.py
spec2sdk/models/templates/base_model.j2
spec2sdk/models/templates/enum.j2
spec2sdk/models/templates/imports.j2
spec2sdk/models/templates/model.j2
spec2sdk/openapi/__init__.py
spec2sdk/openapi/entities.py
spec2sdk/openapi/exceptions.py
spec2sdk/openapi/parsers.py
spec2sdk/openapi/predicates.py
spec2sdk/openapi/resolver.py
spec2sdk/registry.py
spec2sdk/templating.py
spec2sdk-1.0.202510091221.dist-info/LICENSE
spec2sdk-1.0.202510091221.dist-info/METADATA
spec2sdk-1.0.202510091221.dist-info/WHEEL
spec2sdk-1.0.202510091221.dist-info/entry_points.txt
spec2sdk-1.0.202510091221.dist-info/RECORD
