Metadata-Version: 2.3
Name: spec2sdk
Version: 1.0.202510091221
Summary: Generate Pydantic models and API client code from OpenAPI 3.1.x specifications
License: MIT
Keywords: openapi,pydantic,code-generator,openapi-codegen
Author: moneymeets
Author-email: service@moneymeets.com
Requires-Python: >=3.12
Classifier: Development Status :: 3 - Alpha
Classifier: Intended Audience :: Developers
Classifier: Programming Language :: Python :: 3
Classifier: Programming Language :: Python :: 3.12
Classifier: Topic :: Software Development :: Libraries :: Python Modules
Classifier: License :: OSI Approved :: MIT License
Requires-Dist: black
Requires-Dist: jinja2
Requires-Dist: openapi-spec-validator
Requires-Dist: pydantic (>=2,<3)
Requires-Dist: pyhumps
Requires-Dist: ruff
Project-URL: Repository, https://github.com/moneymeets/spec2sdk
